apisbif
