Metadata-Version: 1.1
Name: django-api-sbif
Version: 0.0.3
Summary: API de la Superintendencia de Bancos e Instituciones Financieras de Chile
Home-page: https://github.com/jupitercl/django-api-sbif
Author: Francisco Jordan
Author-email: franciscojordan@live.com
License: MIT
Keywords: django chile api sbif
Platform: UNKNOWN
Classifier: Development Status :: 4 - Beta
Classifier: Environment :: Web Environment
Classifier: Framework :: Django :: 1.11
Classifier: Intended Audience :: Developers
Classifier: License :: OSI Approved :: MIT License
Classifier: Natural Language :: Spanish
Classifier: Operating System :: Unix
Classifier: Programming Language :: Python
Classifier: Programming Language :: Python :: 3
Classifier: Programming Language :: Python :: 3.7
